wynncraft/__init__.py
wynncraft/wynncraft.py
wynncraft/utils/__init__.py
wynncraft/utils/cache.py
wynncraft/utils/constants.py
wynncraft/utils/data.py
wynncraft/utils/rate_limiter.py
wynncraft/utils/request.py
wynncraft-2.0.0.dist-info/LICENSE
wynncraft-2.0.0.dist-info/METADATA
wynncraft-2.0.0.dist-info/WHEEL
wynncraft-2.0.0.dist-info/top_level.txt
wynncraft-2.0.0.dist-info/RECORD
