Metadata-Version: 2.1
Name: wynncraft
Version: 2.0.0
Summary: A wrapper for the Wynncraft API.
Home-page: https://github.com/martinkovacs/wynncraft-python
Author: Martin Kovács
Author-email: martin.k.kovacs@gmail.com
Classifier: Programming Language :: Python :: 3
Classifier: License :: OSI Approved :: MIT License
Classifier: Operating System :: OS Independent
Requires-Python: >=3.6
License-File: LICENSE
